{
  "defaultApp": "launcher",
  "pane_decorator_expanded": false,
  "layout_transitions": {
    "enabled": true,
    "duration_ms": 300,
    "easing": "smoothstep",
    "min_threshold": 3
  },
  "effects": {
    "bindings": [
      {
        "event": "pane.active",
        "target": "pane",
        "effect": "fadeTint",
        "params": {
          "color": "bg.base",
          "intensity": 0.35,
          "duration_ms": 400
        }
      },
      {
        "event": "pane.resizing",
        "target": "pane",
        "effect": "fadeTint",
        "params": {
          "color": "border.resizing",
          "intensity": 0.2,
          "duration_ms": 160
        }
      },
      {
        "event": "workspace.control",
        "target": "workspace",
        "effect": "rainbow",
        "params": {
          "speed_hz": 0.5
        }
      }
    ]
  },
  "screensaver": {
    "enabled": false,
    "timeout_minutes": 5,
    "effect": "crypt",
    "fade_style": "dissolve",
    "fade_in_seconds": 5,
    "fade_out_seconds": 0.5,
    "lock_enabled": false,
    "lock_timeout_minutes": 15
  }
}
